<?xml version="1.0"?>
<!--<!DOCTYPE metadata SYSTEM "http://www.esri.com/metadata/esriprof80.dtd">-->
<metadata xml:lang="en"><Esri><CreaDate>20130829</CreaDate><CreaTime>15095200</CreaTime><SyncOnce>TRUE</SyncOnce><MetaID>{F13B3783-CE3A-459F-8067-23A310D8598B}</MetaID></Esri><idinfo><citation><citeinfo><onlink Sync="TRUE">\\SUJITHA-PC\J$\wanted_List\CONTOURS\Sea_Land_Contour Poly\100m_contour</onlink></citeinfo></citation></idinfo><distInfo><distributor><distorTran><onLineSrc><linkage Sync="TRUE">file://\\SUJITHA-PC\J$\wanted_List\CONTOURS\Sea_Land_Contour Poly\100m_contour</linkage><protocol Sync="TRUE">Local Area Network</protocol></onLineSrc></distorTran></distributor></distInfo><dataqual><lineage><procstep><procdesc Sync="TRUE">Dataset copied.</procdesc><srcused Sync="TRUE">C:\ACD\MB Project\MBProject\100m_contour</srcused><date Sync="TRUE">20120502</date><time Sync="TRUE">15445800</time></procstep><procstep><procdesc Sync="TRUE">Dataset copied.</procdesc><srcused Sync="TRUE">J:\wanted_List\CONTOURS\New_Plc_coast_bathydata\100m_contour</srcused><procdate Sync="TRUE">20130829</procdate><proctime Sync="TRUE">15095200</proctime></procstep></lineage></dataqual></metadata>
